kapten/__init__.py
kapten/cli.py
kapten/exceptions.py
kapten/log.py
kapten/slack.py
kapten/tool.py
kapten-1.3.dist-info/METADATA
kapten-1.3.dist-info/WHEEL
kapten-1.3.dist-info/entry_points.txt
kapten-1.3.dist-info/top_level.txt
kapten-1.3.dist-info/RECORD
