Metadata-Version: 2.1
Name: kapten
Version: 1.3
Summary: Auto deploy of Docker Swarm services
Home-page: https://github.com/5monkeys/kapten
Author: Jonas Lundberg
Author-email: jonas@5monkeys.se
License: MIT
Keywords: docker,swarm,stack,service,auto,deploy
Platform: UNKNOWN
Classifier: Development Status :: 5 - Production/Stable
Classifier: Environment :: Console
Classifier: Intended Audience :: Developers
Classifier: License :: OSI Approved :: MIT License
Classifier: Operating System :: OS Independent
Classifier: Programming Language :: Python
Classifier: Programming Language :: Python :: 3
Classifier: Programming Language :: Python :: 3.5
Classifier: Programming Language :: Python :: 3.6
Classifier: Programming Language :: Python :: 3.7
Classifier: Programming Language :: Python :: 3.8
Requires-Dist: docker
